mindbot/__init__.py
mindbot/audio.py
mindbot/client.py
mindbot/image.py
mindbot/search.py
mindbot/text.py
mindbot/vision.py
testmindbotai-1.0.0.dist-info/LICENSE
testmindbotai-1.0.0.dist-info/METADATA
testmindbotai-1.0.0.dist-info/WHEEL
testmindbotai-1.0.0.dist-info/top_level.txt
testmindbotai-1.0.0.dist-info/RECORD
