Metadata-Version: 2.1
Name: testmindbotai
Version: 1.0.0
Summary: The official Python library for the MindBot API.
Home-page: https://github.com/AhmedHelmy-STEM
Author: Ahmed Helmy Ali Eletr
Author-email: ahmedhelmy.stem@gmail.com
Classifier: Programming Language :: Python :: 3
Classifier: License :: OSI Approved :: MIT License
Classifier: Operating System :: OS Independent
Requires-Python: >=3.6
License-File: LICENSE
Requires-Dist: google-generativeai
Requires-Dist: Flask
Requires-Dist: pandas
Requires-Dist: Pillow
Requires-Dist: requests
Requires-Dist: fpdf
